{
  "games": [
    {
      "id": "game001",
      "name": "Mario Odyssey",
      "image": "",
      "info": "En Super Mario Odyssey, los jugadores controlan a Mario mientras viaja a trav칠s de diversos reinos en su nave, la Odyssey, con el objetivo de rescatar a la Princesa Peach de los planes de boda de Bowser. Cada reino es un mundo abierto lleno de secretos, acertijos y desaf칤os que culminan en la obtenci칩n de Energilunas, necesarias para avanzar a nuevas 치reas. Una mec치nica destacada es la colaboraci칩n con Cappy, un sombrero sensible que permite a Mario capturar y tomar el control de enemigos y objetos, a침adiendo profundidad y variedad a la jugabilidad.",
      "genre": [
        "plataformas",
        "acci칩n",
        "aventura",
        "mundo abierto"
      ],
      "plataform": [
        "nintendo Switch"
      ],
      "developer": " Nintendo EPD (Entertainment Planning & Development)",
      "release date": "27 de Octubre de 2017",
      "awards": [
        "Game Critics Awards 2017",
        "Golden Joystick Awards 2017",
        "The Game Awards 2017",
        "D.I.C.E. Awards 2018",
        "British Academy Games Awards (BAFTA) 2018",
        "Famitsu Awards 2017",
        "NAVGTR Awards 2018"
      ],
      "copiesSold": "28,21 millones de copias vendidas"
    },
    {
      "id": "game002",
      "name": "bloodborne",
      "image": "",
      "info": "Bloodborne es un Action-RPG que incorpora elementos de exploraci칩n y combate en tiempo real. Los jugadores asumen el papel de un cazador en la ciudad ficticia de Yharnam, enfrent치ndose a criaturas grotescas y desentra침ando misterios oscuros. El juego se destaca por su alta dificultad, recompensando la estrategia y la habilidad del jugador.",
      "genre": [
        "acci칩n",
        "rol",
        "combate en tiempo real"
      ],
      "plataform": [
        "Playstarion 4"
      ],
      "developer": "From Software",
      "release date": "24 de marzo de 2015",
      "awards": [
        "The Game Awards 2015: Nominado a Juego del A침o.",
        "British Academy Games Awards (BAFTA) 2016: Ganador en la categor칤a de Logro en Dise침o de Juego.",
        "D.I.C.E. Awards 2016: Ganador en la categor칤a de Logro Sobresaliente en Direcci칩n de Juego."
      ],
      "copiesSold": "7,46 millones de copias vendidas"
    },
    {
      "id": "game003",
      "name": "Lies of P",
      "image": "",
      "info": "Lies of P es un videojuego del g칠nero soulslike. Basado libremente en la novela 'Las aventuras de Pinocho' de Carlo Collodi, el juego ofrece una reinterpretaci칩n oscura y madura del cl치sico cuento.",
      "genre": [
        "accion",
        "aventura",
        "rol"
      ],
      "plataform": [
        "layStation 4",
        "PlayStation 5",
        "Windows",
        "Xbox One",
        "Xbox Series X/S."
      ],
      "developer": "Round8 Studio",
      "release date": "18 de septiembre de 2023",
      "awards": [
        ""
      ],
      "copiesSold": "1 millon de copias vendidas"
    },
    {
      "id": "game004",
      "name": "Black Myth Wukong",
      "image": "",
      "info": "Este juego de rol y acci칩n en tercera persona incorpora elementos soulslike, ofreciendo combates desafiantes y una narrativa profunda. Los jugadores controlan a Sun Wukong, el Rey Mono, utilizando su bast칩n m치gico y habilidades especiales en un mundo inspirado en la mitolog칤a china.",
      "genre": [
        "rol",
        "acci칩n",
        "aventura"
      ],
      "plataform": [
        "layStation 5",
        "Microsoft Windows",
        "Xbox Series X/S"
      ],
      "developer": "Game Science",
      "release date": "20 de agosto de 2024",
      "awards": [
        "Golden Joystick Awards 2024",
        "Game Awards 2024"
      ],
      "copiesSold": "10 millones de copias vendidas "
    },
    {
      "id": "game005",
      "name": "Metroid Dread",
      "image": "",
      "info": "Metroid Dread es un juego de acci칩n y aventura en 2D que contin칰a la historia de Samus Aran en su lucha contra los enemigos intergal치cticos. El juego destaca por su atm칩sfera tensa, exploraci칩n de mundos alien칤genas y un sistema de combate fluido que desaf칤a a los jugadores con secuencias de plataformas y enfrentamientos contra jefes.",
      "genre": [
        "acci칩n",
        "aventura",
        "plataformas",
        "sci-fi"
      ],
      "plataform": [
        "nintendo Switch"
      ],
      "developer": "Nintendo EPD",
      "release date": "8 de octubre de 2021",
      "awards": [
        "The Game Awards 2021 - Mejor Juego de Acci칩n",
        "Golden Joystick Awards 2021 - Mejor Juego de Acci칩n"
      ],
      "copiesSold": "2.74 millones de copias vendidas"
    },
    {
      "id": "game006",
      "name": "Rise of the Ronin",
      "image": "",
      "info": "Rise of the Ronin es un juego de rol y acci칩n de mundo abierto ambientado en el Jap칩n del siglo XIX, durante el per칤odo Bakumatsu. Los jugadores controlan a los Hermanos Blade, personajes personalizables que se ven envueltos en conflictos hist칩ricos y luchas internas mientras exploran ciudades como Yokohama, Edo y Kioto, participando en eventos que llevaron a la Restauraci칩n Meiji.",
      "genre": [
        "rol",
        "acci칩n",
        "aventura",
        "mundo abierto"
      ],
      "plataform": [
        "PlayStation 5",
        "Microsoft Windows"
      ],
      "developer": "Team Ninja",
      "release date": "22 de marzo de 2024",
      "awards": [
        ""
      ],
      "copiesSold": "5 millones de copias vendidas"
    },
    {
      "id": "game007",
      "name": "Assassin's Creed Valhalla",
      "image": "",
      "info": "Assassin's Creed Valhalla es un juego de acci칩n y aventura de mundo abierto donde los jugadores asumen el rol de Eivor, un guerrero vikingo, mientras lidera su clan en su viaje desde Noruega hacia las tierras de Inglaterra. El juego combina combates 칠picos, exploraci칩n, y una narrativa inmersiva centrada en la conquista y supervivencia en un mundo lleno de mitolog칤a y pol칤tica.",
      "genre": [
        "acci칩n",
        "aventura",
        "mundo abierto",
        "rol"
      ],
      "plataform": [
        "PlayStation 4",
        "PlayStation 5",
        "Xbox One",
        "Xbox Series X/S",
        "Microsoft Windows",
        "Stadia"
      ],
      "developer": "Ubisoft Montreal",
      "release date": "10 de noviembre de 2020",
      "awards": [
        "The Game Awards 2020 - Nominado a Mejor Juego de Acci칩n/Aventura",
        "Golden Joystick Awards 2020 - Mejor Juego de Aventura",
        "BAFTA Games Awards 2021 - Nominado a Mejor Juego de Acci칩n"
      ],
      "copiesSold": "14,5 millones de copias vendidas"
    },
    {
      "id": "game008",
      "name": "EA Sports FC 25",
      "image": "",
      "info": "EA Sports FC 25 es un videojuego de f칰tbol desarrollado y publicado por Electronic Arts. Es la segunda entrega de la serie EA Sports FC y la trig칠sima segunda si se incluyen las entregas bajo el nombre de FIFA",
      "genre": [
        "deportes",
        "simulaci칩n",
        "f칰tbol"
      ],
      "plataform": [
        "Nintendo Switch",
        "PlayStation 4",
        "PlayStation 5",
        "Microsoft Windows",
        "Xbox One",
        "Xbox Series X/S"
      ],
      "developer": "Electronic Arts",
      "release date": "27 de septiembre de 2024",
      "awards": [
        "The Game Awards 2024 - Nominado a Mejor Juego de Deportes",
        "Golden Joystick Awards 2024 - Nominado a Mejor Juego de Deportes"
      ],
      "copiesSold": "10 millones de copias vendidas "
    },
    {
      "id": "game009",
      "name": "God of War (2018)",
      "image": "",
      "info": "God of War (2018) es un juego de acci칩n y aventura que reinventa la cl치sica saga de Kratos, llev치ndola a la mitolog칤a n칩rdica. El juego sigue a Kratos y su hijo Atreus mientras enfrentan a dioses, monstruos y desaf칤os mientras buscan cumplir el 칰ltimo deseo de la madre de Atreus. Con un combate fluido, una historia emocional y un mundo abierto, el t칤tulo se convirti칩 en uno de los m치s aclamados de la generaci칩n.",
      "genre": [
        "acci칩n",
        "aventura",
        "rol",
        "mundo abierto"
      ],
      "plataform": [
        "PlayStation 4",
        "Microsoft Windows"
      ],
      "developer": "Santa Monica Studio",
      "release date": "20 de abril de 2018",
      "awards": [
        "The Game Awards 2018 - Juego del A침o",
        "Golden Joystick Awards 2018 - Mejor Juego de Acci칩n",
        "BAFTA Games Awards 2019 - Mejor Juego",
        "D.I.C.E. Awards 2019 - Juego del A침o"
      ],
      "copiesSold": "20 millones de copias vendidas"
    },
    {
      "id": "game010",
      "name": "Grand Theft Auto V",
      "image": "",
      "info": "Grand Theft Auto V es un juego de acci칩n y aventura de mundo abierto desarrollado por Rockstar North. Los jugadores controlan a tres protagonistas (Michael, Trevor y Franklin) en la ciudad ficticia de Los Santos, basada en Los 츼ngeles. El juego ofrece una amplia gama de actividades, desde misiones principales hasta actividades secundarias como deportes, veh칤culos y robos. Su modo multijugador, GTA Online, ha sido un 칠xito continuo con actualizaciones regulares.",
      "genre": [
        "acci칩n",
        "aventura",
        "mundo abierto"
      ],
      "plataform": [
        "PlayStation 3",
        "PlayStation 4",
        "PlayStation 5",
        "Xbox 360",
        "Xbox One",
        "Xbox Series X/S",
        "Microsoft Windows"
      ],
      "developer": "Rockstar North",
      "release date": "17 de septiembre de 2013",
      "awards": [
        "The Game Awards 2013 - Nominado a Juego del A침o",
        "Golden Joystick Awards 2013 - Mejor Juego de Acci칩n",
        "BAFTA Games Awards 2014 - Mejor Juego",
        "D.I.C.E. Awards 2014 - Juego del A침o"
      ],
      "copiesSold": "160 millones de copias vendidas"
    },
    {
      "id": "game011",
      "name": "Pok칠mon Legends: Arceus",
      "image": "",
      "info": "Pok칠mon Legends: Arceus es un juego de rol de acci칩n desarrollado por Game Freak. Ambientado en la regi칩n de Hisui, una versi칩n primitiva de Sinnoh, el juego introduce una jugabilidad m치s abierta y din치mica que los juegos tradicionales de la serie. Los jugadores asumen el rol de un joven investigador de la Pok칠dex que explora un mundo abierto, captura Pok칠mon y se enfrenta a desaf칤os mientras busca a Arceus, el Pok칠mon creador del universo.",
      "genre": [
        "rol",
        "acci칩n",
        "aventura",
        "mundo abierto"
      ],
      "plataform": [
        "Nintendo Switch"
      ],
      "developer": "Game Freak",
      "release date": "28 de enero de 2022",
      "awards": [
        "The Game Awards 2022 - Nominado a Mejor Juego de Rol",
        "Golden Joystick Awards 2022 - Mejor Juego de Rol",
        "Famitsu Awards 2022 - Mejor Juego de Rol"
      ],
      "copiesSold": "14,63 millones de copias vendidas"
    },
    {
      "id": "game012",
      "name": "Halo Infinite",
      "image": "",
      "info": "Halo Infinite es un juego de disparos en primera persona desarrollado por 343 Industries. La historia sigue al Jefe Maestro mientras lucha contra el Covenant y el nuevo enemigo, los 'Banished', en un mundo abierto dentro del anillo Halo. El juego ofrece una experiencia de campa침a profunda, un multijugador competitivo gratuito y gr치ficos de 칰ltima generaci칩n, destacando la libertad en la exploraci칩n del anillo Halo.",
      "genre": [
        "disparos en primera persona",
        "acci칩n",
        "ciencia ficci칩n",
        "multijugador"
      ],
      "plataform": [
        "Xbox One",
        "Xbox Series X/S",
        "Microsoft Windows"
      ],
      "developer": "343 Industries",
      "release date": "8 de diciembre de 2021",
      "awards": [
        "The Game Awards 2021 - Nominado a Mejor Juego de Acci칩n",
        "Golden Joystick Awards 2021 - Nominado a Mejor Juego de Acci칩n",
        "BAFTA Games Awards 2022 - Nominado a Mejor Juego de Acci칩n"
      ],
      "copiesSold": "M치s de 10 millones de copias"
    },
    {
      "id": "game013",
      "name": "Red Dead Redemption 2",
      "image": "",
      "info": "Red Dead Redemption 2 es un juego de acci칩n y aventura de mundo abierto desarrollado por Rockstar Games. Ambientado en 1899, el juego sigue a Arthur Morgan, un miembro de la banda de Dutch van der Linde, mientras navega por un mundo lleno de traiciones, lealtades rotas y un envejecido lejano oeste. El t칤tulo se destaca por su detallado mundo abierto, su narrativa profunda y su jugabilidad que combina exploraci칩n, combate y actividades secundarias.",
      "genre": [
        "acci칩n",
        "aventura",
        "mundo abierto",
        "rol"
      ],
      "plataform": [
        "PlayStation 4",
        "Xbox One",
        "Microsoft Windows",
        "Stadia"
      ],
      "developer": "Rockstar Games",
      "release date": "26 de octubre de 2018",
      "awards": [
        "The Game Awards 2018 - Juego del A침o",
        "Golden Joystick Awards 2018 - Mejor Juego de Acci칩n/Aventura",
        "BAFTA Games Awards 2019 - Mejor Juego",
        "D.I.C.E. Awards 2019 - Juego del A침o"
      ],
      "copiesSold": "50 millones de copias vendidas"
    },
    {
      "id": "game014",
      "name": "Resident Evil Village (Resident Evil 8)",
      "image": "",
      "info": "Resident Evil Village es un juego de terror y supervivencia en tercera persona, desarrollado por Capcom. Continuando la historia de Ethan Winters, quien busca a su hija secuestrada en un misterioso pueblo europeo, el juego combina elementos cl치sicos de la serie con una jugabilidad m치s centrada en la acci칩n. Enfrentando criaturas sobrenaturales y monstruos, el t칤tulo ofrece una atm칩sfera tensa y una narrativa profunda en el universo de Resident Evil.",
      "genre": [
        "terror",
        "supervivencia",
        "acci칩n",
        "aventura"
      ],
      "plataform": [
        "PlayStation 4",
        "PlayStation 5",
        "Xbox One",
        "Xbox Series X/S",
        "Microsoft Windows"
      ],
      "developer": "Capcom",
      "release date": "7 de mayo de 2021",
      "awards": [
        "The Game Awards 2021 - Mejor Juego de Acci칩n/Aventura",
        "Golden Joystick Awards 2021 - Mejor Juego de Acci칩n",
        "BAFTA Games Awards 2022 - Mejor Juego de Terror"
      ],
      "copiesSold": "12 millones de copias vendidas"
    },
    {
      "id": "game015",
      "name": "inFAMOUS",
      "image": "",
      "info": "inFAMOUS es un juego de acci칩n y aventura de mundo abierto desarrollado por Sucker Punch Productions. Los jugadores controlan a Cole MacGrath, un mensajero que, despu칠s de un extra침o accidente, adquiere poderes el칠ctricos. El juego ofrece la posibilidad de elegir entre dos caminos: el h칠roe o el villano, lo que afecta las misiones, el entorno y la narrativa. El juego es conocido por su jugabilidad din치mica y las decisiones morales que el jugador debe tomar.",
      "genre": [
        "acci칩n",
        "aventura",
        "mundo abierto",
        "superpoderes"
      ],
      "plataform": [
        "PlayStation 3"
      ],
      "developer": "Sucker Punch Productions",
      "release date": "26 de mayo de 2009",
      "awards": [
        "Spike Video Game Awards 2009 - Mejor Juego de Acci칩n",
        "Golden Joystick Awards 2009 - Nominado a Mejor Juego de Acci칩n"
      ],
      "copiesSold": "6 millones de copias vendidas"
    },
    {
      "id": "game016",
      "name": "Guitar Hero III: Legends of Rock",
      "image": "",
      "info": "Guitar Hero III: Legends of Rock es un juego de ritmo y m칰sica desarrollado por Neversoft y publicado por Activision. Es la tercera entrega de la serie Guitar Hero y presenta una amplia lista de canciones de rock cl치sico y contempor치neo. Los jugadores usan un controlador de guitarra para tocar las notas al ritmo de la m칰sica. Este t칤tulo introdujo el modo multijugador en l칤nea y la posibilidad de tocar como personajes legendarios como Slash, de Guns N' Roses.",
      "genre": [
        "ritmo",
        "musical",
        "acci칩n"
      ],
      "plataform": [
        "PlayStation 2",
        "PlayStation 3",
        "Xbox 360",
        "Wii",
        "Microsoft Windows"
      ],
      "developer": "Neversoft",
      "release date": "28 de octubre de 2007",
      "awards": [
        "Spike Video Game Awards 2007 - Mejor Juego de Ritmo",
        "Golden Joystick Awards 2008 - Mejor Juego Musical",
        "BAFTA Games Awards 2008 - Mejor Juego Musical"
      ],
      "copiesSold": "14 millones de copias vendidas"
    },
    {
      "id": "game017",
      "name": "Prince of Persia: The Lost Crown",
      "image": "",
      "info": "Prince of Persia: The Lost Crown es un videojuego de acci칩n y aventura de desplazamiento lateral desarrollado y publicado por Ubisoft. El juego presenta a Sargon, un joven miembro del clan guerrero Los Inmortales, quien debe viajar a la ciudad maldita del Monte Qaf para rescatar al Pr칤ncipe Ghassan, secuestrado por el general traidor Vahram. Sargon posee habilidades acrob치ticas y puede utilizar poderes temporales para superar obst치culos y enemigos. El mundo del juego est치 interconectado, ofreciendo elementos de exploraci칩n y resoluci칩n de acertijos al estilo Metroidvania.",
      "genre": [
        "acci칩n",
        "aventura",
        "plataformas",
        "Metroidvania"
      ],
      "plataform": [
        "PlayStation 4",
        "PlayStation 5",
        "Xbox One",
        "Xbox Series X/S",
        "Nintendo Switch",
        "Microsoft Windows"
      ],
      "developer": "Ubisoft Montpellier",
      "release date": "18 de enero de 2024",
      "awards": [
        "Metacritic Score: 86",
        "IGN Best Action-Adventure Game 2024",
        "Golden Joystick Awards 2024 - Nominado a Mejor Juego de Acci칩n"
      ],
      "copiesSold": "1 mill칩n de copias vendidas"
    },
    {
      "id": "game018",
      "name": "Sekiro: Shadows Die Twice",
      "image": "",
      "info": "Sekiro: Shadows Die Twice es un juego de acci칩n y aventura desarrollado por FromSoftware, conocido por su dificultad desafiante. Ambientado en el Jap칩n feudal, los jugadores controlan a un shinobi llamado Sekiro, quien busca rescatar a su joven se침or y vengar su p칠rdida. El juego se destaca por su combate fluido, que combina la precisi칩n de la espada con mec치nicas de parry y sigilo. A diferencia de otros t칤tulos de FromSoftware, Sekiro se enfoca en una narrativa m치s directa y un estilo de combate centrado en la habilidad y la estrategia.",
      "genre": [
        "acci칩n",
        "aventura",
        "rol",
        "hack and slash"
      ],
      "plataform": [
        "PlayStation 4",
        "Xbox One",
        "Microsoft Windows"
      ],
      "developer": "FromSoftware",
      "release date": "22 de marzo de 2019",
      "awards": [
        "The Game Awards 2019 - Juego del A침o",
        "Golden Joystick Awards 2019 - Mejor Juego de Acci칩n",
        "BAFTA Games Awards 2020 - Mejor Juego",
        "D.I.C.E. Awards 2020 - Juego del A침o"
      ],
      "copiesSold": "5 millones de copias vendidas"
    },
    {
      "id": "game019",
      "name": "Ghost of Tsushima",
      "image": "",
      "info": "Ghost of Tsushima es un juego de acci칩n y aventura en mundo abierto desarrollado por Sucker Punch Productions. Ambientado en el Jap칩n feudal, los jugadores controlan a Jin Sakai, un samur치i que lucha contra la invasi칩n mongola en la isla de Tsushima. El juego destaca por su bell칤simo mundo abierto inspirado en el Jap칩n tradicional, su combate fluido basado en espada y el uso de sigilo y t치cticas para derrotar a los enemigos. La narrativa sigue el viaje de Jin mientras lucha por mantener su honor y adaptarse a un nuevo estilo de combate para salvar a su pueblo.",
      "genre": [
        "acci칩n",
        "aventura",
        "mundo abierto",
        "samur치is"
      ],
      "plataform": [
        "PlayStation 4",
        "PlayStation 5"
      ],
      "developer": "Sucker Punch Productions",
      "release date": "17 de julio de 2020",
      "awards": [
        "The Game Awards 2020 - Mejor Juego de Aventura",
        "Golden Joystick Awards 2020 - Mejor Juego de Acci칩n",
        "BAFTA Games Awards 2021 - Mejor Juego de Acci칩n",
        "D.I.C.E. Awards 2021 - Juego de Aventura del A침o"
      ],
      "copiesSold": "8 millones de copias vendidas"
    },
    {
      "id": "game020",
      "name": "Elden Ring",
      "image": "",
      "info": "Elden Ring es un juego de rol y acci칩n de mundo abierto desarrollado por FromSoftware y dirigido por Hidetaka Miyazaki, en colaboraci칩n con el autor de 'Juego de Tronos', George R. R. Martin. El juego se sit칰a en el mundo de The Lands Between, donde los jugadores asumen el papel de un personaje conocido como el 'Tarnished', que busca restaurar el Elden Ring y convertirse en el Elden Lord. El juego combina la dificultad caracter칤stica de FromSoftware con un mundo expansivo y un sistema de combate innovador.",
      "genre": [
        "rol",
        "acci칩n",
        "aventura",
        "mundo abierto"
      ],
      "plataform": [
        "PlayStation 4",
        "PlayStation 5",
        "Xbox One",
        "Xbox Series X/S",
        "Microsoft Windows"
      ],
      "developer": "FromSoftware",
      "release date": "25 de febrero de 2022",
      "awards": [
        "The Game Awards 2022 - Juego del A침o",
        "Golden Joystick Awards 2022 - Mejor Juego de Acci칩n/Aventura",
        "BAFTA Games Awards 2022 - Mejor Juego",
        "D.I.C.E. Awards 2022 - Juego del A침o"
      ],
      "copiesSold": "20 millones de copias vendidas"
    }
  ],
  "commentaries": [
    {
      "id": "coment001",
      "userName": "MarioFan123",
      "favs": "游",
      "comment": "춰Este juego es incre칤ble! La jugabilidad es fluida y los niveles son tan creativos. Cappy es un gran a침adido al juego. Definitivamente uno de los mejores juegos de la serie Mario.",
      "dayPublish": "12 de mayo de 2020",
      "gameId": "game001"
    },
    {
      "id": "coment002",
      "userName": "GamerX92",
      "favs": "游녩",
      "comment": "Es un buen juego, pero no me gusta c칩mo algunas mec치nicas, como las capturas, afectan la jugabilidad. Algunas se sienten demasiado forzadas. A칰n as칤, es divertido.",
      "dayPublish": "5 de octubre de 2021",
      "gameId": "game001"
    },
    {
      "id": "coment003",
      "userName": "Luna_Sun",
      "favs": "游녩",
      "comment": "Lo encontr칠 bastante aburrido despu칠s de un par de horas. Hay algo en la estructura que no me engancha tanto como otros juegos de Mario. Aun as칤, la gr치fica es preciosa.",
      "dayPublish": "23 de noviembre de 2019",
      "gameId": "game001"
    },
    {
      "id": "coment004",
      "userName": "PixelMaster",
      "favs": "游",
      "comment": "춰Uno de los mejores t칤tulos de la Nintendo Switch! Me encantan las zonas abiertas y la sensaci칩n de exploraci칩n. Un gran homenaje a la franquicia.",
      "dayPublish": "18 de enero de 2021",
      "gameId": "game001"
    },
    {
      "id": "coment005",
      "userName": "HunterMaster",
      "favs": "游",
      "comment": "Bloodborne es una obra maestra de FromSoftware. La atm칩sfera oscura y la jugabilidad desafiante hacen que cada batalla sea inolvidable. Es uno de los mejores juegos de acci칩n que he jugado.",
      "dayPublish": "15 de junio de 2018",
      "gameId": "game002"
    },
    {
      "id": "coment006",
      "userName": "NightmareWalker",
      "favs": "游녩",
      "comment": "Aunque la ambientaci칩n es impresionante, me result칩 muy dif칤cil y frustrante. La dificultad puede ser un obst치culo para disfrutar del juego en su totalidad.",
      "dayPublish": "29 de agosto de 2019",
      "gameId": "game002"
    },
    {
      "id": "coment007",
      "userName": "BloodMoonKing",
      "favs": "游녩",
      "comment": "No soy fan del estilo de combate y el mundo tan oscuro. La falta de explicaciones en la historia me dej칩 perdido, y las mec치nicas no son de mi agrado.",
      "dayPublish": "11 de noviembre de 2020",
      "gameId": "game002"
    },
    {
      "id": "coment008",
      "userName": "DarkSoulsFan01",
      "favs": "游",
      "comment": "Un juego extremadamente desafiante, pero tan gratificante cuando superas los enemigos m치s dif칤ciles. La historia est치 oculta de forma intrigante y la jugabilidad es fluida.",
      "dayPublish": "3 de febrero de 2021",
      "gameId": "game002"
    },
    {
      "id": "coment009",
      "userName": "PuppetMaster23",
      "favs": "游",
      "comment": "Lies of P es un juego impresionante. La historia oscura y el mundo steampunk est치n muy bien logrados. El combate es desafiante pero gratificante. 춰No puedo esperar a ver m치s!",
      "dayPublish": "14 de septiembre de 2023",
      "gameId": "game003"
    },
    {
      "id": "coment010",
      "userName": "GameSeeker85",
      "favs": "游녩",
      "comment": "Aunque la atm칩sfera es interesante, me parece que el juego no ofrece nada realmente innovador en comparaci칩n con otros juegos del g칠nero. El combate puede volverse mon칩tono despu칠s de un tiempo.",
      "dayPublish": "8 de octubre de 2023",
      "gameId": "game003"
    },
    {
      "id": "coment011",
      "userName": "DarkLoreFan",
      "favs": "游녩",
      "comment": "A pesar de tener una narrativa prometedora, el ritmo del juego no me enganch칩. La mec치nica de combate es s칩lida, pero la historia se siente forzada.",
      "dayPublish": "25 de noviembre de 2023",
      "gameId": "game003"
    },
    {
      "id": "coment012",
      "userName": "EpicGamer92",
      "favs": "游",
      "comment": "Me ha sorprendido gratamente. El dise침o del mundo es fascinante y el combate tiene mucha profundidad. Un juego que todo fan de los soulslike deber칤a probar.",
      "dayPublish": "19 de diciembre de 2023",
      "gameId": "game003"
    },
    {
      "id": "coment013",
      "userName": "WukongFan23",
      "favs": "游",
      "comment": "춰Este juego tiene un potencial incre칤ble! Los gr치ficos y el combate son impresionantes. La mezcla de mitolog칤a china con acci칩n es un sue침o hecho realidad. 춰Definitivamente uno de los m치s esperados!",
      "dayPublish": "1 de diciembre de 2023",
      "gameId": "game004"
    },
    {
      "id": "coment014",
      "userName": "GamerX_21",
      "favs": "游녩",
      "comment": "El juego se ve impresionante, pero a칰n se siente muy crudo. La jugabilidad necesita pulirse m치s antes de que pueda ser algo realmente grande. A칰n tengo dudas sobre c칩mo se desarrollar치.",
      "dayPublish": "16 de enero de 2024",
      "gameId": "game004"
    },
    {
      "id": "coment015",
      "userName": "DragonSlayer98",
      "favs": "游녩",
      "comment": "A pesar de la incre칤ble direcci칩n art칤stica, el combate se siente algo repetitivo y lento. Necesitan trabajar m치s en la fluidez de las mec치nicas si quieren competir con otros t칤tulos de acci칩n.",
      "dayPublish": "4 de febrero de 2024",
      "gameId": "game004"
    },
    {
      "id": "coment016",
      "userName": "LegendaryPlayer",
      "favs": "游",
      "comment": "Me encanta la mitolog칤a detr치s del juego, y el sistema de combate parece muy pulido. Espero que logren mantener la calidad que muestran en los avances. 춰Va a ser 칠pico!",
      "dayPublish": "28 de noviembre de 2023",
      "gameId": "game004"
    },
    {
      "id": "coment017",
      "userName": "SamusFan88",
      "favs": "游",
      "comment": "Metroid Dread es una incre칤ble continuaci칩n de la saga. La jugabilidad es perfecta, el ambiente es tenso y el regreso a la acci칩n 2D es todo lo que esper치bamos. 춰Samus sigue siendo la mejor!",
      "dayPublish": "9 de octubre de 2021",
      "gameId": "game005"
    },
    {
      "id": "coment018",
      "userName": "SpaceExplorer101",
      "favs": "游녩",
      "comment": "El juego se ve genial, pero la dificultad me resulta excesiva y las mec치nicas de los enemigos 'EMMIs' se sienten demasiado forzadas. No es tan disfrutable como los juegos anteriores de la saga.",
      "dayPublish": "16 de octubre de 2021",
      "gameId": "game005"
    },
    {
      "id": "coment019",
      "userName": "RetroGamer22",
      "favs": "游녩",
      "comment": "Aunque la jugabilidad es s칩lida, no puedo evitar sentir que el juego se queda corto en comparaci칩n con otros t칤tulos de la franquicia. Algunas mec치nicas podr칤an haberse mejorado.",
      "dayPublish": "5 de noviembre de 2021",
      "gameId": "game005"
    },
    {
      "id": "coment020",
      "userName": "SciFiLover",
      "favs": "游",
      "comment": "Es una joya. La atm칩sfera es perfecta, el combate es desafiante y la historia es incre칤blemente intrigante. 춰Un gran regreso para Samus!",
      "dayPublish": "19 de octubre de 2021",
      "gameId": "game005"
    },
    {
      "id": "coment021",
      "userName": "RoninMaster",
      "favs": "游",
      "comment": "Rise of the Ronin ha capturado perfectamente la esencia de los samur치is y el Jap칩n feudal. Los gr치ficos son impresionantes, y el combate se siente fluido y brutal. Este juego promete ser una joya.",
      "dayPublish": "3 de diciembre de 2023",
      "gameId": "game006"
    },
    {
      "id": "coment022",
      "userName": "KatanaWarrior",
      "favs": "游녩",
      "comment": "Aunque la historia y la ambientaci칩n son interesantes, el combate no me ha convencido. El ritmo es un poco lento y las mec치nicas de lucha parecen demasiado r칤gidas.",
      "dayPublish": "15 de enero de 2024",
      "gameId": "game006"
    },
    {
      "id": "coment023",
      "userName": "BushidoGamer",
      "favs": "游",
      "comment": "Una experiencia inmersiva. El mundo abierto, la historia profunda y el sistema de combate me tienen enganchado. Es lo que siempre quise de un juego de samur치is.",
      "dayPublish": "25 de noviembre de 2023",
      "gameId": "game006"
    },
    {
      "id": "coment024",
      "userName": "ShogunPlayer01",
      "favs": "游녩",
      "comment": "No me termin칩 de enganchar. A pesar de tener buenos elementos, el juego no se siente tan fluido y a veces se vuelve repetitivo. Ten칤a expectativas m치s altas.",
      "dayPublish": "8 de diciembre de 2023",
      "gameId": "game006"
    },
    {
      "id": "coment025",
      "userName": "VikingLegend98",
      "favs": "游",
      "comment": "Assassin's Creed Valhalla es una obra maestra. La historia es envolvente, el mundo abierto es vasto y hermoso, y las mec치nicas de combate son incre칤blemente satisfactorias. Me ha dejado sin palabras.",
      "dayPublish": "2 de noviembre de 2020",
      "gameId": "game007"
    },
    {
      "id": "coment026",
      "userName": "EivorWarrior",
      "favs": "游녩",
      "comment": "El juego es bonito, pero se siente repetitivo. Las misiones secundarias son muy similares entre s칤 y la historia no tiene la misma profundidad que otros juegos de la saga.",
      "dayPublish": "10 de diciembre de 2020",
      "gameId": "game007"
    },
    {
      "id": "coment027",
      "userName": "StealthAssassin",
      "favs": "游",
      "comment": "Me encanta c칩mo han mejorado el combate y la exploraci칩n en el mundo abierto. Aunque algunas mec치nicas podr칤an pulirse, el juego es una excelente adici칩n a la serie.",
      "dayPublish": "18 de noviembre de 2020",
      "gameId": "game007"
    },
    {
      "id": "coment028",
      "userName": "BerserkerHunter",
      "favs": "游녩",
      "comment": "No soy fan de la direcci칩n que ha tomado la saga. El juego es demasiado largo y se siente algo pesado a veces. Las mec치nicas de combate, aunque buenas, no logran mantener mi inter칠s.",
      "dayPublish": "21 de diciembre de 2020",
      "gameId": "game007"
    },
    {
      "id": "coment029",
      "userName": "FootballFanX",
      "favs": "游",
      "comment": "춰EA Sports FC 25 ha superado mis expectativas! Los gr치ficos son impresionantes, la jugabilidad es fluida y las nuevas mec치nicas de juego realmente mejoran la experiencia. 춰Este es el mejor simulador de f칰tbol hasta ahora!",
      "dayPublish": "5 de octubre de 2024",
      "gameId": "game008"
    },
    {
      "id": "coment030",
      "userName": "GameCritic2024",
      "favs": "游녩",
      "comment": "El juego es bastante bueno, pero algunas animaciones siguen siendo poco realistas y el modo carrera podr칤a tener m치s profundidad. En general, siento que no hay grandes avances respecto a los t칤tulos anteriores.",
      "dayPublish": "15 de octubre de 2024",
      "gameId": "game008"
    },
    {
      "id": "coment031",
      "userName": "SoccerLover92",
      "favs": "游녩",
      "comment": "Aunque el juego tiene mejoras gr치ficas, la jugabilidad sigue siendo muy similar a los anteriores. Me esperaba algo m치s innovador en este nuevo cap칤tulo de la serie.",
      "dayPublish": "20 de octubre de 2024",
      "gameId": "game008"
    },
    {
      "id": "coment032",
      "userName": "ProGamer22",
      "favs": "游",
      "comment": "춰Una gran adici칩n a la saga! El modo Ultimate Team est치 m치s pulido que nunca y el sistema de habilidades mejora mucho la din치mica de juego. Definitivamente el juego de f칰tbol m치s realista hasta la fecha.",
      "dayPublish": "28 de septiembre de 2024",
      "gameId": "game008"
    },
    {
      "id": "coment033",
      "userName": "KratosFan92",
      "favs": "游",
      "comment": "춰Este juego es una obra maestra! La historia de Kratos y Atreus es profundamente emotiva, el combate es brutal y la atm칩sfera de todo el mundo n칩rdico es impresionante. Definitivamente uno de los mejores juegos de la generaci칩n.",
      "dayPublish": "20 de abril de 2018",
      "gameId": "game009"
    },
    {
      "id": "coment034",
      "userName": "FuryHunter",
      "favs": "游녩",
      "comment": "Aunque el juego es visualmente hermoso y tiene una historia s칩lida, la jugabilidad me pareci칩 repetitiva. Algunas mec치nicas de combate no me convencieron y me cost칩 un poco engancharme.",
      "dayPublish": "5 de mayo de 2018",
      "gameId": "game009"
    },
    {
      "id": "coment035",
      "userName": "Godslayer_88",
      "favs": "游",
      "comment": "Una experiencia inolvidable. Kratos muestra una nueva faceta de su personalidad y la relaci칩n con Atreus es maravillosa. El combate fluido y el dise침o del mundo n칩rdico son impresionantes.",
      "dayPublish": "10 de abril de 2018",
      "gameId": "game009"
    },
    {
      "id": "coment036",
      "userName": "VikingSoul",
      "favs": "游녩",
      "comment": "Aunque el juego tiene una buena narrativa, se siente m치s como un juego de aventuras gen칠rico que un God of War cl치sico. Extra침칠 el estilo de combate r치pido y fren칠tico de los anteriores.",
      "dayPublish": "18 de abril de 2018",
      "gameId": "game009"
    },
    {
      "id": "coment037",
      "userName": "LosSantosKing",
      "favs": "游",
      "comment": "GTA V es un juego legendario. La historia es incre칤blemente entretenida, el mundo abierto es vasto y lleno de actividades, y el modo online siempre tiene algo nuevo para ofrecer. 춰Una obra maestra de la industria!",
      "dayPublish": "17 de septiembre de 2013",
      "gameId": "game010"
    },
    {
      "id": "coment038",
      "userName": "RebelGamer101",
      "favs": "游녩",
      "comment": "Aunque el mundo es grande, siento que el juego est치 muy enfocado en el aspecto de los disparos y los veh칤culos. Las misiones a veces son repetitivas y el enfoque en el crimen me dej칩 algo insatisfecho.",
      "dayPublish": "22 de septiembre de 2013",
      "gameId": "game010"
    },
    {
      "id": "coment039",
      "userName": "StreetRacer99",
      "favs": "游",
      "comment": "La cantidad de cosas que puedes hacer en GTA V es impresionante. Desde carreras hasta misiones de historia, pasando por actividades aleatorias en la ciudad. Cada rinc칩n de Los Santos tiene algo que explorar.",
      "dayPublish": "5 de octubre de 2013",
      "gameId": "game010"
    },
    {
      "id": "coment040",
      "userName": "ViceCityVibes",
      "favs": "游녩",
      "comment": "El juego es grandioso, pero siento que la historia de los tres protagonistas no est치 tan bien conectada. Adem치s, algunas misiones se sienten forzadas y no tan naturales como en otros GTA.",
      "dayPublish": "12 de octubre de 2013",
      "gameId": "game010"
    },
    {
      "id": "coment041",
      "userName": "Pok칠monMaster01",
      "favs": "游",
      "comment": "춰Este es el juego de Pok칠mon que estaba esperando! La jugabilidad abierta, la exploraci칩n y la captura de Pok칠mon de manera m치s libre y din치mica hacen que la experiencia sea fresca y emocionante. Arceus tiene todo lo que los fans quer칤an.",
      "dayPublish": "28 de enero de 2022",
      "gameId": "game011"
    },
    {
      "id": "coment042",
      "userName": "Pok칠Fan88",
      "favs": "游녩",
      "comment": "Aunque la idea de un mundo abierto en Pok칠mon es genial, siento que los gr치ficos no son tan buenos y la historia es algo simple. Esperaba una experiencia m치s pulida y con m치s contenido.",
      "dayPublish": "2 de febrero de 2022",
      "gameId": "game011"
    },
    {
      "id": "coment043",
      "userName": "LegendaryTrainer",
      "favs": "游",
      "comment": "Este es el mejor juego de Pok칠mon en a침os. La libertad de explorar el mundo y la captura de Pok칠mon de forma tan natural me ha enganchado por completo. El cambio de f칩rmula ha sido un acierto.",
      "dayPublish": "5 de febrero de 2022",
      "gameId": "game011"
    },
    {
      "id": "coment044",
      "userName": "EeveeFan22",
      "favs": "游녩",
      "comment": "A pesar de ser innovador, el juego se siente un poco vac칤o en algunas 치reas. Las misiones secundarias se repiten mucho y no hay tanto contenido como esperaba en un mundo tan grande.",
      "dayPublish": "10 de febrero de 2022",
      "gameId": "game011"
    },
    {
      "id": "coment045",
      "userName": "Spartan112",
      "favs": "游",
      "comment": "Halo Infinite ha regresado con todo. La campa침a tiene una historia envolvente y el mundo abierto es impresionante. El regreso de Master Chief es 칠pico, y el modo multijugador sigue siendo una de las mejores experiencias en shooters.",
      "dayPublish": "8 de diciembre de 2021",
      "gameId": "game012"
    },
    {
      "id": "coment046",
      "userName": "CovenantHunter",
      "favs": "游녩",
      "comment": "Aunque el juego tiene grandes gr치ficos y una jugabilidad s칩lida, el modo multijugador est치 un poco desbalanceado y la falta de contenido en el lanzamiento me decepcion칩. Hab칤a muchas expectativas",
      "dayPublish": "15 de diciembre de 2021",
      "gameId": "game012"
    },
    {
      "id": "coment047",
      "userName": "MasterChiefFan24",
      "favs": "游",
      "comment": "Un regreso impresionante para la saga. La campa침a es muy entretenida, y la exploraci칩n en el mundo abierto es una gran adici칩n. No puedo esperar para ver qu칠 m치s traer치n en futuras actualizaciones.",
      "dayPublish": "10 de diciembre de 2021",
      "gameId": "game012"
    },
    {
      "id": "coment048",
      "userName": "ODST_Elite",
      "favs": "游녩",
      "comment": "El juego est치 bien, pero siento que le falta algo. La historia no me atrap칩 tanto como en otros Halo y el modo multijugador tiene demasiado 'microtransacciones'. Necesita m치s pulido.",
      "dayPublish": "18 de diciembre de 2021",
      "gameId": "game012"
    },
    {
      "id": "coment049",
      "userName": "OutlawLegend",
      "favs": "游",
      "comment": "Red Dead Redemption 2 es una obra maestra. La historia es profunda, los personajes son complejos, y el mundo abierto es impresionante. Cada detalle de este juego est치 cuidado al m치ximo. 춰Una experiencia inolvidable!",
      "dayPublish": "26 de octubre de 2018",
      "gameId": "game013"
    },
    {
      "id": "coment050",
      "userName": "Gunslinger23",
      "favs": "游녩",
      "comment": "El juego tiene una gran historia y un mundo incre칤blemente detallado, pero a veces se siente un poco lento. Las misiones secundarias pueden ser tediosas y la jugabilidad no siempre es tan fluida como esperaba.",
      "dayPublish": "30 de octubre de 2018",
      "gameId": "game013"
    },
    {
      "id": "coment051",
      "userName": "VikingOutlaw",
      "favs": "游",
      "comment": "Una de las mejores experiencias de juego que he tenido. La narrativa es 칠pica, el mundo es tan detallado que puedes perderte explorando, y las mec치nicas de caza y supervivencia a침aden una capa extra de realismo.",
      "dayPublish": "1 de noviembre de 2018",
      "gameId": "game013"
    },
    {
      "id": "coment052",
      "userName": "RedDeadFan94",
      "favs": "游녩",
      "comment": "El juego es incre칤blemente detallado, pero a veces la jugabilidad se siente lenta y las interacciones con otros personajes pueden ser largas y tediosas. No es para todos.",
      "dayPublish": "5 de noviembre de 2018",
      "gameId": "game013"
    },
    {
      "id": "coment053",
      "userName": "UmbrellaSurvivor",
      "favs": "游",
      "comment": "Resident Evil Village es una obra maestra. La mezcla de acci칩n y horror es perfecta, y la historia est치 llena de giros emocionantes. Los personajes como Lady Dimitrescu son inolvidables. 춰Un imprescindible para los fans del g칠nero!",
      "dayPublish": "7 de mayo de 2021",
      "gameId": "game014"
    },
    {
      "id": "coment054",
      "userName": "EthanHunter",
      "favs": "游녩",
      "comment": "Aunque la jugabilidad es buena y los gr치ficos son impresionantes, la historia no me termin칩 de enganchar. Adem치s, el cambio hacia m치s acci칩n en comparaci칩n con los anteriores juegos de la saga no fue lo que esperaba.",
      "dayPublish": "10 de mayo de 2021",
      "gameId": "game014"
    },
    {
      "id": "coment055",
      "userName": "ResidentEvilFan92",
      "favs": "游",
      "comment": "Este juego me dej칩 sin aliento. El dise침o de los enemigos, la atm칩sfera y las mec치nicas de juego hacen que cada segundo sea emocionante. Me encant칩 la experiencia en su totalidad.",
      "dayPublish": "12 de mayo de 2021",
      "gameId": "game014"
    },
    {
      "id": "coment056",
      "userName": "LickerKing",
      "favs": "游녩",
      "comment": "El juego es entretenido, pero siento que perdi칩 algo de la atm칩sfera de terror cl치sico de Resident Evil. Hay m치s acci칩n y menos suspenso, lo que no me parece tan interesante como los t칤tulos anteriores.",
      "dayPublish": "15 de mayo de 2021",
      "gameId": "game014"
    },
    {
      "id": "coment057",
      "userName": "ElectricHero",
      "favs": "游",
      "comment": "Un juego incre칤blemente divertido. La mec치nica de poderes el칠ctricos es muy satisfactoria y la historia te mantiene enganchado. Adem치s, las decisiones morales a침aden una gran rejugabilidad.",
      "dayPublish": "12 de junio de 2009",
      "gameId": "game015"
    },
    {
      "id": "coment058",
      "userName": "DarkKarma",
      "favs": "游녩",
      "comment": "El concepto es genial, pero la historia no me atrap칩 tanto como esperaba. Adem치s, los controles pueden sentirse un poco toscos en algunas secciones del juego.",
      "dayPublish": "15 de junio de 2009",
      "gameId": "game015"
    },
    {
      "id": "coment059",
      "userName": "ConduitX",
      "favs": "游",
      "comment": "El sistema de karma y la exploraci칩n hacen que este juego sea muy especial. Cole es un gran protagonista y las habilidades el칠ctricas son s칰per entretenidas. Lo recomiendo totalmente.",
      "dayPublish": "20 de junio de 2009",
      "gameId": "game015"
    },
    {
      "id": "coment060",
      "userName": "NeonRider",
      "favs": "游녩",
      "comment": "Buen juego, pero siento que la ciudad se siente vac칤a en algunos momentos y que la IA de los enemigos no es tan desafiante. Podr칤a haber tenido m치s variedad en las misiones secundarias.",
      "dayPublish": "25 de junio de 2009",
      "gameId": "game015"
    },
    {
      "id": "coment061",
      "userName": "RockstarX",
      "favs": "游",
      "comment": "Este juego es una leyenda. La selecci칩n de canciones es incre칤ble y la jugabilidad sigue siendo adictiva hasta el d칤a de hoy. 춰Nada como enfrentarse a Slash en un duelo de guitarra!",
      "dayPublish": "28 de octubre de 2007",
      "gameId": "game016"
    },
    {
      "id": "coment062",
      "userName": "SoloMaster",
      "favs": "游녩",
      "comment": "Es un buen juego, pero en dificultad alta algunas canciones son simplemente frustrantes. Se siente injusto en lugar de desafiante en ciertos momentos.",
      "dayPublish": "2 de noviembre de 2007",
      "gameId": "game016"
    },
    {
      "id": "coment063",
      "userName": "MetalFreak99",
      "favs": "游",
      "comment": "La mejor entrega de Guitar Hero sin duda. Horas de diversi칩n con amigos y un gran setlist que incluye cl치sicos del rock y metal. No me canso de jugarlo.",
      "dayPublish": "5 de noviembre de 2007",
      "gameId": "game016"
    },
    {
      "id": "coment064",
      "userName": "StringBreaker",
      "favs": "游녩",
      "comment": "Despu칠s de un tiempo, se siente repetitivo. Me hubiera gustado m치s variedad en los modos de juego. Aun as칤, es entretenido por un rato.",
      "dayPublish": "10 de noviembre de 2007",
      "gameId": "game016"
    },
    {
      "id": "coment065",
      "userName": "TimeWarrior",
      "favs": "游",
      "comment": "Un regreso incre칤ble para la saga. La jugabilidad es fluida, los combates son din치micos y el dise침o de niveles es espectacular. Se siente como una mezcla perfecta entre lo cl치sico y lo moderno.",
      "dayPublish": "19 de enero de 2024",
      "gameId": "game017"
    },
    {
      "id": "coment066",
      "userName": "SandsOfTime",
      "favs": "游녩",
      "comment": "No est치 mal, pero esperaba algo m치s ambicioso. La historia es un poco simple y el estilo visual no me termin칩 de convencer. Aun as칤, la jugabilidad es s칩lida.",
      "dayPublish": "22 de enero de 2024",
      "gameId": "game017"
    },
    {
      "id": "coment067",
      "userName": "BladeMaster77",
      "favs": "游",
      "comment": "Me encant칩. Es un metroidvania con una gran ambientaci칩n y mec치nicas muy bien logradas. Cada nuevo poder que consigues hace que la exploraci칩n sea m치s interesante.",
      "dayPublish": "25 de enero de 2024",
      "gameId": "game017"
    },
    {
      "id": "coment068",
      "userName": "LostTraveler",
      "favs": "游녩",
      "comment": "Tiene buenas ideas, pero esperaba m치s profundidad en la historia. Adem치s, algunas secciones se sienten repetitivas. No es malo, pero no es el mejor de la saga.",
      "dayPublish": "30 de enero de 2024",
      "gameId": "game017"
    },
    {
      "id": "coment069",
      "userName": "WolfOfAshina",
      "favs": "游",
      "comment": "Uno de los mejores juegos que he jugado. La jugabilidad es desafiante pero extremadamente satisfactoria. Cada pelea se siente como un duelo de habilidad. 춰Obra maestra!",
      "dayPublish": "25 de marzo de 2019",
      "gameId": "game018"
    },
    {
      "id": "coment070",
      "userName": "StealthNinja",
      "favs": "游녩",
      "comment": "El juego es hermoso y la jugabilidad es 칰nica, pero la dificultad es exagerada. No es accesible para todos, y eso puede ser frustrante.",
      "dayPublish": "28 de marzo de 2019",
      "gameId": "game018"
    },
    {
      "id": "coment071",
      "userName": "ShinobiMaster",
      "favs": "游",
      "comment": "Cada enfrentamiento es un reto que te obliga a mejorar. La ambientaci칩n es incre칤ble y la historia, aunque m치s sutil, es muy buena. Una joya para los fans de los juegos dif칤ciles.",
      "dayPublish": "2 de abril de 2019",
      "gameId": "game018"
    },
    {
      "id": "coment072",
      "userName": "ParryOrDie",
      "favs": "游녩",
      "comment": "Los combates son intensos, pero el sistema de postura puede volverse repetitivo. Adem치s, no tener un modo f치cil hace que muchos jugadores no puedan disfrutarlo.",
      "dayPublish": "5 de abril de 2019",
      "gameId": "game018"
    },
    {
      "id": "coment073",
      "userName": "SamuraiLegend",
      "favs": "游",
      "comment": "Un juego impresionante. La ambientaci칩n es hermosa, el combate es fluido y la historia es 칠pica. Me sent칤 como un verdadero samur치i explorando Tsushima.",
      "dayPublish": "17 de julio de 2020",
      "gameId": "game019"
    },
    {
      "id": "coment074",
      "userName": "RoninLost",
      "favs": "游녩",
      "comment": "Gr치ficamente es incre칤ble, pero la jugabilidad puede volverse repetitiva despu칠s de un tiempo. Adem치s, la IA de los enemigos no es muy desafiante.",
      "dayPublish": "20 de julio de 2020",
      "gameId": "game019"
    },
    {
      "id": "coment075",
      "userName": "WayOfTheBlade",
      "favs": "游",
      "comment": "El mejor juego de samur치is que he jugado. La exploraci칩n sin marcadores, las peleas con katana y la m칰sica lo hacen una experiencia inolvidable.",
      "dayPublish": "25 de julio de 2020",
      "gameId": "game019"
    },
    {
      "id": "coment076",
      "userName": "ShadowAssassin",
      "favs": "游녩",
      "comment": "La historia es buena, pero esperaba m치s profundidad en las decisiones del protagonista. Adem치s, las misiones secundarias son muy repetitivas.",
      "dayPublish": "30 de julio de 2020",
      "gameId": "game019"
    },
    {
      "id": "coment077",
      "userName": "LostInTheLandsBetween",
      "favs": "游녩",
      "comment": "El juego tiene un mundo impresionante, pero la falta de un sistema de gu칤a puede hacerlo frustrante. No es para todos, especialmente si no tienes paciencia para explorar sin indicaciones.",
      "dayPublish": "1 de marzo de 2022",
      "gameId": "game020"
    },
    {
      "id": "coment078",
      "userName": "TarnishedWarrior",
      "favs": "游",
      "comment": "Una obra maestra absoluta. El mundo abierto es gigantesco y lleno de secretos, los combates son desafiantes y la exploraci칩n es simplemente adictiva. 춰El mejor juego de FromSoftware hasta ahora!",
      "dayPublish": "27 de febrero de 2022",
      "gameId": "game020"
    },
    {
      "id": "coment079",
      "userName": "EldenChampion",
      "favs": "游",
      "comment": "Nunca hab칤a sentido tanta libertad en un juego de FromSoftware. La combinaci칩n entre Dark Souls y mundo abierto es perfecta. Cada zona es una obra de arte.",
      "dayPublish": "5 de marzo de 2022",
      "gameId": "game020"
    },
    {
      "id": "coment080",
      "userName": "TooHard4Me",
      "favs": "游녩",
      "comment": "Los gr치ficos y la m칰sica son geniales, pero la dificultad es absurda en algunas partes. No hay un modo f치cil, lo que hace que muchos jugadores no puedan disfrutarlo.",
      "dayPublish": "10 de marzo de 2022",
      "gameId": "game020"
    }
  ]
}